README.md
setup.py
src/kaiheila/__init__.py
src/kaiheila/application/__init__.py
src/kaiheila/application/context.py
src/kaiheila/application/exceptions.py
src/kaiheila/application/group.py
src/kaiheila/application/logger.py
src/kaiheila/application/utils.py
src/kaiheila/application/event/__init__.py
src/kaiheila/application/event/kaiheila.py
src/khlbot_bcc.egg-info/PKG-INFO
src/khlbot_bcc.egg-info/SOURCES.txt
src/khlbot_bcc.egg-info/dependency_links.txt
src/khlbot_bcc.egg-info/requires.txt
src/khlbot_bcc.egg-info/top_level.txt