Metadata-Version: 2.1
Name: khlbot-bcc
Version: 1.0.3
Summary: 开黑啦 Bot websocket API 的 Python 实现.
Home-page: https://github.com/purofle/khlbot
Author: purofle
Author-email: 3272912942@qq.com
License: UNKNOWN
Project-URL: Bug Tracker, https://github.com/purofle/khlbot/issues
Platform: UNKNOWN
Classifier: Programming Language :: Python :: 3
Classifier: License :: OSI Approved :: GNU Affero General Public License v3 or later (AGPLv3+)
Classifier: Operating System :: OS Independent
Requires-Python: >=3.7
